Star_Utils/__init__.py
Star_Utils/__version__.py
Star_Utils/cog.py
Star_Utils/cogsutils.py
Star_Utils/context.py
Star_Utils/loop.py
Star_Utils/menus.py
Star_Utils/sentry.py
Star_Utils/settings.py
Star_Utils/shared_cog.py
Star_Utils/views.py
Starry_Utils-1.4.dist-info/LICENCE
Starry_Utils-1.4.dist-info/METADATA
Starry_Utils-1.4.dist-info/WHEEL
Starry_Utils-1.4.dist-info/top_level.txt
Starry_Utils-1.4.dist-info/RECORD
