Metadata-Version: 2.1
Name: Starry-Utils
Version: 1.4
Summary: Utils for Star-Cogs.
Home-page: https://github.com/LeDeathAmongst/Star_Utils
Author: Star
Author-email: skylar.rae.val@proton.me
Classifier: Programming Language :: Python :: 3
Classifier: Operating System :: OS Independent
Requires-Python: >=3.9.1
License-File: LICENCE
Requires-Dist: sentry-sdk
Requires-Dist: colorama
